pydantic2/__init__.py
pydantic2/utils/__init__.py
pydantic2/utils/cli.py
pydantic2/utils/logger.py
pydantic2-2.1.1.dist-info/LICENSE
pydantic2-2.1.1.dist-info/METADATA
pydantic2-2.1.1.dist-info/WHEEL
pydantic2-2.1.1.dist-info/entry_points.txt
pydantic2-2.1.1.dist-info/top_level.txt
pydantic2-2.1.1.dist-info/RECORD
