Metadata-Version: 2.2
Name: pydantic2
Version: 2.1.1
Summary: A powerful AI framework with structured Pydantic responses, flexible LLM integration, and advanced agent capabilities
Home-page: https://pydantic.unrealos.com/
Author: Unrealos
Author-email: info@unrealos.com
License: MIT
Project-URL: Homepage, https://pydantic.unrealos.com/
Project-URL: Documentation, https://pydantic.unrealos.com/
Project-URL: Source, https://github.com/markolofsen/pydantic2
Project-URL: Tracker, https://github.com/markolofsen/pydantic2/issues
Classifier: Development Status :: 4 - Beta
Classifier: Intended Audience :: Developers
Classifier: Intended Audience :: Information Technology
Classifier: Intended Audience :: Science/Research
Classifier: Topic :: Software Development :: Libraries
Classifier: Topic :: Scientific/Engineering :: Artificial Intelligence
Classifier: Topic :: Text Processing :: Linguistic
Classifier: Programming Language :: Python :: 3.7
Classifier: Programming Language :: Python :: 3.8
Classifier: Programming Language :: Python :: 3.9
Classifier: Programming Language :: Python :: 3.10
Classifier: Programming Language :: Python :: 3.11
Classifier: License :: OSI Approved :: MIT License
Classifier: Operating System :: OS Independent
Requires-Python: >=3.11
License-File: LICENSE
Requires-Dist: pydantic-ai>=0.0.40
Requires-Dist: colorlog>=6.7.0
Requires-Dist: typing-extensions>=4.10.0
Requires-Dist: peewee>=3.17.0
Requires-Dist: beautifulsoup4>=4.12.0
Requires-Dist: pyyaml>=6.0.2
Requires-Dist: python-dotenv>=1.0.1
Requires-Dist: datasette>=0.65.1
Requires-Dist: click>=8.1.7
Requires-Dist: aiohttp>=3.11.14
